{
"meta":{"test_sets":[],"test_metrics":[],"learn_metrics":[{"best_value":"Min","name":"Logloss"}],"launch_mode":"Train","parameters":"","iteration_count":63,"learn_sets":["learn"],"name":"experiment"},
"iterations":[
{"learn":[0.6387539464],"iteration":0,"passed_time":0.003121684914,"remaining_time":0.1935444646},
{"learn":[0.5961982343],"iteration":1,"passed_time":0.006102067068,"remaining_time":0.1861130456},
{"learn":[0.5627313413],"iteration":2,"passed_time":0.008633043533,"remaining_time":0.1726608707},
{"learn":[0.5382845254],"iteration":3,"passed_time":0.01166371921,"remaining_time":0.1720398584},
{"learn":[0.5180159529],"iteration":4,"passed_time":0.01419633873,"remaining_time":0.1646775293},
{"learn":[0.5028459433],"iteration":5,"passed_time":0.01699090535,"remaining_time":0.1614136009},
{"learn":[0.4895848712],"iteration":6,"passed_time":0.01966549888,"remaining_time":0.157323991},
{"learn":[0.4761088245],"iteration":7,"passed_time":0.02226686624,"remaining_time":0.1530847054},
{"learn":[0.4657559739],"iteration":8,"passed_time":0.02479849392,"remaining_time":0.1487909635},
{"learn":[0.4570808364],"iteration":9,"passed_time":0.02734257475,"remaining_time":0.1449156462},
{"learn":[0.4498901355],"iteration":10,"passed_time":0.02993756024,"remaining_time":0.141523012},
{"learn":[0.4428773087],"iteration":11,"passed_time":0.03266067399,"remaining_time":0.1388078645},
{"learn":[0.4369516964],"iteration":12,"passed_time":0.03443957193,"remaining_time":0.1324598921},
{"learn":[0.4319808551],"iteration":13,"passed_time":0.03698650808,"remaining_time":0.1294527783},
{"learn":[0.4279286227],"iteration":14,"passed_time":0.0384867278,"remaining_time":0.123157529},
{"learn":[0.4249619256],"iteration":15,"passed_time":0.03991409205,"remaining_time":0.1172476454},
{"learn":[0.4222031513],"iteration":16,"passed_time":0.04248805846,"remaining_time":0.1149676876},
{"learn":[0.4191439516],"iteration":17,"passed_time":0.04510806047,"remaining_time":0.1127701512},
{"learn":[0.4174319107],"iteration":18,"passed_time":0.04766966389,"remaining_time":0.1103929058},
{"learn":[0.4159442134],"iteration":19,"passed_time":0.04887076739,"remaining_time":0.1050721499},
{"learn":[0.4140605097],"iteration":20,"passed_time":0.05147281602,"remaining_time":0.102945632},
{"learn":[0.4122457766],"iteration":21,"passed_time":0.05416579373,"remaining_time":0.1009453429},
{"learn":[0.4100134589],"iteration":22,"passed_time":0.05678623656,"remaining_time":0.09875867228},
{"learn":[0.4097352995],"iteration":23,"passed_time":0.05790992611,"remaining_time":0.09410362993},
{"learn":[0.4082696749],"iteration":24,"passed_time":0.06051743489,"remaining_time":0.09198650104},
{"learn":[0.4068445185],"iteration":25,"passed_time":0.06308283537,"remaining_time":0.08977172726},
{"learn":[0.4059015245],"iteration":26,"passed_time":0.06565876543,"remaining_time":0.08754502057},
{"learn":[0.4053820423],"iteration":27,"passed_time":0.06711009424,"remaining_time":0.0838876178},
{"learn":[0.4044220126],"iteration":28,"passed_time":0.06965344371,"remaining_time":0.08166265815},
{"learn":[0.4032113845],"iteration":29,"passed_time":0.07231842937,"remaining_time":0.07955027231},
{"learn":[0.401667285],"iteration":30,"passed_time":0.07508581545,"remaining_time":0.07750793853},
{"learn":[0.4003226296],"iteration":31,"passed_time":0.07766607356,"remaining_time":0.07523900876},
{"learn":[0.3999334287],"iteration":32,"passed_time":0.08020650761,"remaining_time":0.07291500692},
{"learn":[0.3995501221],"iteration":33,"passed_time":0.08300365904,"remaining_time":0.07079723859},
{"learn":[0.3987624899],"iteration":34,"passed_time":0.08552240276,"remaining_time":0.06841792221},
{"learn":[0.3985567237],"iteration":35,"passed_time":0.08674102885,"remaining_time":0.06505577164},
{"learn":[0.3979953633],"iteration":36,"passed_time":0.08966480574,"remaining_time":0.06300770133},
{"learn":[0.3977433906],"iteration":37,"passed_time":0.09144056785,"remaining_time":0.06015826832},
{"learn":[0.3975379475],"iteration":38,"passed_time":0.09315394395,"remaining_time":0.05732550397},
{"learn":[0.3969947556],"iteration":39,"passed_time":0.09573165733,"remaining_time":0.05504570296},
{"learn":[0.3961906656],"iteration":40,"passed_time":0.09833828447,"remaining_time":0.05276688435},
{"learn":[0.3960698234],"iteration":41,"passed_time":0.1009917587,"remaining_time":0.05049587936},
{"learn":[0.3955819657],"iteration":42,"passed_time":0.1038948271,"remaining_time":0.0483231754},
{"learn":[0.3951242363],"iteration":43,"passed_time":0.1065726466,"remaining_time":0.0460200065},
{"learn":[0.3940629829],"iteration":44,"passed_time":0.1092388746,"remaining_time":0.04369554984},
{"learn":[0.3934516209],"iteration":45,"passed_time":0.1118309447,"remaining_time":0.04132882738},
{"learn":[0.3931943656],"iteration":46,"passed_time":0.1145340212,"remaining_time":0.03899030508},
{"learn":[0.3930394123],"iteration":47,"passed_time":0.1170486272,"remaining_time":0.036577696},
{"learn":[0.3926247026],"iteration":48,"passed_time":0.1195504194,"remaining_time":0.03415726268},
{"learn":[0.3920670341],"iteration":49,"passed_time":0.122219122,"remaining_time":0.03177697171},
{"learn":[0.3920109645],"iteration":50,"passed_time":0.1236422784,"remaining_time":0.0290923008},
{"learn":[0.3915185749],"iteration":51,"passed_time":0.1262917352,"remaining_time":0.02671555936},
{"learn":[0.3910620198],"iteration":52,"passed_time":0.1291790342,"remaining_time":0.02437340268},
{"learn":[0.3906577205],"iteration":53,"passed_time":0.1319025387,"remaining_time":0.02198375645},
{"learn":[0.390482654],"iteration":54,"passed_time":0.1343994618,"remaining_time":0.01954901263},
{"learn":[0.3902513257],"iteration":55,"passed_time":0.1370771712,"remaining_time":0.0171346464},
{"learn":[0.3900188891],"iteration":56,"passed_time":0.1396284354,"remaining_time":0.01469773004},
{"learn":[0.389943542],"iteration":57,"passed_time":0.1422851456,"remaining_time":0.01226596083},
{"learn":[0.3898164413],"iteration":58,"passed_time":0.1448608352,"remaining_time":0.009821073576},
{"learn":[0.3894269319],"iteration":59,"passed_time":0.147470999,"remaining_time":0.007373549948},
{"learn":[0.3891728852],"iteration":60,"passed_time":0.1501359746,"remaining_time":0.004922490971},
{"learn":[0.3890015874],"iteration":61,"passed_time":0.1527461483,"remaining_time":0.002463647554},
{"learn":[0.3887129675],"iteration":62,"passed_time":0.1553209463,"remaining_time":0}
]}